flask_api_key/__init__.py
flask_api_key/api_key.py
flask_api_key/api_key_manager.py
flask_api_key/decorators.py
flask_api_key/exceptions.py
flask_api_key/utils.py
flask_api_key-0.2.12.dist-info/LICENSE
flask_api_key-0.2.12.dist-info/METADATA
flask_api_key-0.2.12.dist-info/WHEEL
flask_api_key-0.2.12.dist-info/top_level.txt
flask_api_key-0.2.12.dist-info/RECORD
