Metadata-Version: 2.1
Name: flask-api-key
Version: 0.2.12
Summary: Provide api-key based auth for your apis.
License: MIT
Keywords: api,auth
Classifier: Development Status :: 5 - Production/Stable
Classifier: Environment :: Web Environment
Classifier: Framework :: Flask
Classifier: License :: OSI Approved :: MIT License
License-File: LICENSE
Requires-Dist: flask
Requires-Dist: passlib
Requires-Dist: importlib-metadata ; python_version < "3.8"
